cexpl/__init__.py
cexpl/__main__.py
cexpl/cli.py
cexpl/lib.py
cexpl-0.1.0.data/data/share/man/man1/cexpl.1
cexpl-0.1.0.dist-info/LICENSE
cexpl-0.1.0.dist-info/METADATA
cexpl-0.1.0.dist-info/WHEEL
cexpl-0.1.0.dist-info/entry_points.txt
cexpl-0.1.0.dist-info/top_level.txt
cexpl-0.1.0.dist-info/RECORD
