Metadata-Version: 2.1
Name: cexpl
Version: 0.1.0
Summary: Command-line tool to interact with Compiler Explorer
Home-page: https://github.com/xfgusta/cexpl
Author: Gustavo Costa
Author-email: xfgusta@gmail.com
License: MIT
Project-URL: Repository, https://github.com/xfgusta/cexpl
Project-URL: Issues, https://github.com/xfgusta/cexpl/issues
Keywords: cli,lib,library,api,command-line,compiler,compilation,compiler-explorer,godbolt
Classifier: Environment :: Console
Classifier: Intended Audience :: Information Technology
Classifier: Intended Audience :: Developers
Classifier: License :: OSI Approved :: MIT License
Classifier: Operating System :: OS Independent
Classifier: Programming Language :: Python :: 3.6
Classifier: Topic :: Utilities
Requires-Python: >=3.6
License-File: LICENSE
Requires-Dist: requests
Requires-Dist: colorama
